[{"ID":0,"burst":18,"arrival":9,"priority":0,"timePassed":0,"algoUsed":"","completionTime":0,"firstRun":0},{"ID":1,"burst":6,"arrival":14,"priority":0,"timePassed":0,"algoUsed":"","completionTime":0,"firstRun":0},{"ID":2,"burst":17,"arrival":10,"priority":0,"timePassed":0,"algoUsed":"","completionTime":0,"firstRun":0},{"ID":3,"burst":10,"arrival":15,"priority":0,"timePassed":0,"algoUsed":"","completionTime":0,"firstRun":0},{"ID":4,"burst":15,"arrival":10,"priority":0,"timePassed":0,"algoUsed":"","completionTime":0,"firstRun":0},{"ID":5,"burst":6,"arrival":9,"priority":0,"timePassed":0,"algoUsed":"","completionTime":0,"firstRun":0},{"ID":6,"burst":1,"arrival":8,"priority":0,"timePassed":0,"algoUsed":"","completionTime":0,"firstRun":0},{"ID":7,"burst":9,"arrival":10,"priority":0,"timePassed":0,"algoUsed":"","completionTime":0,"firstRun":0},{"ID":8,"burst":1,"arrival":7,"priority":0,"timePassed":0,"algoUsed":"","completionTime":0,"firstRun":0},{"ID":9,"burst":16,"arrival":13,"priority":0,"timePassed":0,"algoUsed":"","completionTime":0,"firstRun":0},{"ID":10,"burst":7,"arrival":13,"priority":0,"timePassed":0,"algoUsed":"","completionTime":0,"firstRun":0},{"ID":11,"burst":16,"arrival":10,"priority":0,"timePassed":0,"algoUsed":"","completionTime":0,"firstRun":0},{"ID":12,"burst":5,"arrival":4,"priority":0,"timePassed":0,"algoUsed":"","completionTime":0,"firstRun":0},{"ID":13,"burst":16,"arrival":12,"priority":0,"timePassed":0,"algoUsed":"","completionTime":0,"firstRun":0},{"ID":14,"burst":16,"arrival":10,"priority":0,"timePassed":0,"algoUsed":"","completionTime":0,"firstRun":0}]